mdbase/__init__.py
mdbase/data.py
mdbase/stats.py
mdbase-0.4.dist-info/LICENCE
mdbase-0.4.dist-info/METADATA
mdbase-0.4.dist-info/WHEEL
mdbase-0.4.dist-info/top_level.txt
mdbase-0.4.dist-info/RECORD
