Metadata-Version: 2.1
Name: mdbase
Version: 0.4
Summary: MDbase :: join + process multiple XLS databases
Home-page: https://github.com/mirekslouf/mdbase/
Author: Mirek Slouf
Author-email: mirek.slouf@gmail.com
License: MIT
Project-URL: Documentation, https://mirekslouf.github.io/mdbase/
Classifier: Programming Language :: Python :: 3
Classifier: License :: OSI Approved :: MIT License
Classifier: Operating System :: OS Independent
Requires-Python: >=3.6
License-File: LICENCE
